README.rst
setup.cfg
setup.py
glot.egg-info/PKG-INFO
glot.egg-info/SOURCES.txt
glot.egg-info/dependency_links.txt
glot.egg-info/requires.txt
glot.egg-info/top_level.txt
scripts/glot
src/glot/__init__.py
src/glot/actions.py
src/glot/connector.py
src/glot/transfer.py