Metadata-Version: 1.0
Name: glot
Version: 0.1.4
Summary: CLI manager for Glossia (https://go-smart.github.io/glossia)
Home-page: http://gosmart-project.eu/
Author: NUMA Engineering Services Ltd.
Author-email: phil.weir@numa.ie
License: UNKNOWN
Platform: UNKNOWN
